gau_python/__init__.py
gau_python/main.py
gau_python/providers/__init__.py
gau_python/providers/commoncrawl.py
gau_python/providers/otx.py
gau_python/providers/wayback.py
gau_python-0.1.8.dist-info/LICENSE
gau_python-0.1.8.dist-info/METADATA
gau_python-0.1.8.dist-info/WHEEL
gau_python-0.1.8.dist-info/top_level.txt
gau_python-0.1.8.dist-info/RECORD
