Metadata-Version: 2.1
Name: gau-python
Version: 0.1.8
Summary: Source: https://github.com/connor-marchand/gau-python
Author-email: Connor Marchand <connor@connormarchand.com>
Project-URL: Homepage, https://github.com/connor-marchand/gau-python
Project-URL: Bug Tracker, https://github.com/connor-marchand/gau-python/issues
Classifier: Programming Language :: Python :: 3
Classifier: License :: OSI Approved :: MIT License
Classifier: Operating System :: OS Independent
Requires-Python: >=3.7
License-File: LICENSE
